zwcv/__init__.py
zwcv/__version__.py
zwcv-0.0.1.dist-info/LICENSE
zwcv-0.0.1.dist-info/METADATA
zwcv-0.0.1.dist-info/WHEEL
zwcv-0.0.1.dist-info/top_level.txt
zwcv-0.0.1.dist-info/RECORD
